webkage/__init__.py
webkage/application.py
webkage/http_response.py
webkage/parser.py
webkage/router.py
webkage-0.6.dist-info/LICENSE
webkage-0.6.dist-info/METADATA
webkage-0.6.dist-info/WHEEL
webkage-0.6.dist-info/top_level.txt
webkage-0.6.dist-info/RECORD
