Metadata-Version: 2.1
Name: webkage
Version: 0.6
Summary: A fast micro web framework
Home-page: https://github.com/thelaycon/webkage
Author: Tobi Balogun
Author-email: btobi49@gmail.com
License: UNKNOWN
Project-URL: Bug Tracker, https://github.com/thelaycon/webkage/issues
Platform: UNKNOWN
Classifier: Programming Language :: Python :: 3
Classifier: License :: OSI Approved :: MIT License
Classifier: Operating System :: OS Independent
Requires-Python: >=3.6
License-File: LICENSE
